{
  "name": "Напиток Aloe Fresh алоэ негазированный 0.5л",
  "unitsOfMeasurement": "шт",
  "step": "1.0",
  "priceRegular": 59.99,
  "priceWithCard": 54.59,
  "promo": null,
  "isNew": false,
  "stockCount": 12,
  "ingredients": "Специально подготовленная вода, сахар, кусочки Алоэ Вера, лимонная кислота Е330 (регулятор кислотности), комплексная пищевая добавка чс-31 (стабилизатор геллановая камедь. регулятор кислотности цитрат натрия, агент антислеживающий карбонат кальция, загуститель конжаковая камедь), ароматизатор, антиокислитель аскорбиновая кислота, консерванты: сорбат калия, бензоат натрия.",
  "information": [
    {
      "value": "Fresh  ",
      "name": "Бренд",
      "unitsOfMeasurement": null,
      "order": 1,
      "isNutrient": false,
      "nutrientName": null
    },
    {
      "value": "Россия",
      "name": "Страна производства",
      "unitsOfMeasurement": null,
      "order": 2,
      "isNutrient": false,
      "nutrientName": null
    },
    {
      "value": "8.9",
      "name": "Углеводы",
      "unitsOfMeasurement": "г",
      "order": 3,
      "isNutrient": true,
      "nutrientName": "углеводы"
    },
    {
      "value": "35",
      "name": "Энергетическая ценность",
      "unitsOfMeasurement": "ккал",
      "order": 4,
      "isNutrient": true,
      "nutrientName": "ккал"
    }
  ]
}