{
  "name": "Краска для волос Garnier Color Naturals белое солнце 10",
  "unitsOfMeasurement": "шт",
  "step": "1.0",
  "priceRegular": 229.99,
  "priceWithCard": 223.09,
  "promo": {
    "discountedPriceRegular": "200.09",
    "discountedPriceWithCard": "194.09",
    "discountPercent": "13",
    "isActive": true
  },
  "isNew": false,
  "stockCount": 19,
  "ingredients": "Aqua / water cetearyl alcohol deceth-3 propylene glycol laureth-12 ammonium hydroxide oleth-30 lauric acid hexadimethrine chloride glycol distearate polyquaternium-6 ethanolamine silica dimethyl silylate p-phenylenediamine ci 77891 / titanium dioxide 4-amino-2-hydroxytoluene p-aminophenol ascorbic acid sodium metabisulfite olea europaea / olive fruit oil 2-methyl-5-hydroxyethylaminophenol dimethicone pentasodium pentetate carbomer resorcinol parfum / fragrance.",
  "information": [
    {
      "value": "Garnier",
      "name": "Бренд",
      "unitsOfMeasurement": null,
      "order": 1,
      "isNutrient": false,
      "nutrientName": null
    },
    {
      "value": "Россия",
      "name": "Страна производства",
      "unitsOfMeasurement": null,
      "order": 2,
      "isNutrient": false,
      "nutrientName": null
    }
  ]
}