{
  "name": "Шоколад Спартак темный с трюфельной начинкой 45г",
  "unitsOfMeasurement": "шт",
  "step": "1.0",
  "priceRegular": "34.99",
  "priceWithCard": "32.19",
  "discountPercent": null,
  "discountedPrice": null,
  "discountIsActive": false,
  "discountExpiresAt": null,
  "isNew": false,
  "stockCount": 19,
  "ingredients": "темная шоколадная масса (сахарная пудра, какое тертое, какао-мало, эквивалент масла-какао (масла растительные (пальмовое, ши), эмульгаторы (лецитин соевый)), эмульгаторы (лецитинсоевый, Е476), ароматизатор натуральный ваниль), сахарная пудра, жир кондитерский (масла растительные (пальмовое, подсолнечное), эмульгатор (моно- и диглицириды жирных кислот), антиокислители (кислота лимонная, токоферолы, концентрат смеси)), какао-порошок, заменитель молочного жира (масла растительные (пальмовое, подсолнечное, соевое, рапсовое, пальмоядровое), антиокислитель (токоферолы, концентрат смеси)), молоко сухое (массовая доля жира 25%), спирт этиловый ректификованный не ниже высшей очистки, эмульгатор (лецитин соевый), ароматизатор ром, продукт может содержать следы глютена, арахиса, орехов, яичных продуктов",
  "information": [
    {
      "value": "Спартак",
      "name": "Бренд",
      "unitsOfMeasurement": null,
      "order": 1,
      "isNutrient": false,
      "nutrientName": null
    },
    {
      "value": "Беларусь",
      "name": "Страна производства",
      "unitsOfMeasurement": null,
      "order": 2,
      "isNutrient": false,
      "nutrientName": null
    },
    {
      "value": "6.5",
      "name": "Белки",
      "unitsOfMeasurement": "г",
      "order": 3,
      "isNutrient": true,
      "nutrientName": "белки"
    },
    {
      "value": "37",
      "name": "Жиры",
      "unitsOfMeasurement": "г",
      "order": 4,
      "isNutrient": true,
      "nutrientName": "жиры"
    },
    {
      "value": "47",
      "name": "Углеводы",
      "unitsOfMeasurement": "г",
      "order": 5,
      "isNutrient": true,
      "nutrientName": "углеводы"
    },
    {
      "value": "550",
      "name": "Энергетическая ценность",
      "unitsOfMeasurement": "ккал",
      "order": 6,
      "isNutrient": true,
      "nutrientName": "ккал"
    }
  ]
}