{
  "name": "Каша Heinz Многозерновая кашка из 5 злаков сухая безмолочная быстрорастворимая 6 месяцев+ 180г",
  "unitsOfMeasurement": "шт",
  "step": "1.0",
  "priceRegular": "175.99",
  "priceWithCard": "170.71",
  "discountPercent": null,
  "discountedPrice": null,
  "discountIsActive": false,
  "discountExpiresAt": null,
  "isNew": false,
  "stockCount": 13,
  "ingredients": "мука (рисовая, овсяная, гречневая, пшеничная, кукурузная), волокна пребиотические",
  "information": [
    {
      "value": "Heinz",
      "name": "Бренд",
      "unitsOfMeasurement": null,
      "order": 1,
      "isNutrient": false,
      "nutrientName": null
    },
    {
      "value": "Россия",
      "name": "Страна производства",
      "unitsOfMeasurement": null,
      "order": 2,
      "isNutrient": false,
      "nutrientName": null
    },
    {
      "value": "9.6",
      "name": "Белки",
      "unitsOfMeasurement": "г",
      "order": 3,
      "isNutrient": true,
      "nutrientName": "белки"
    },
    {
      "value": "2.7",
      "name": "Жиры",
      "unitsOfMeasurement": "г",
      "order": 4,
      "isNutrient": true,
      "nutrientName": "жиры"
    },
    {
      "value": "82.5",
      "name": "Углеводы",
      "unitsOfMeasurement": "г",
      "order": 5,
      "isNutrient": true,
      "nutrientName": "углеводы"
    },
    {
      "value": "390",
      "name": "Энергетическая ценность",
      "unitsOfMeasurement": "ккал",
      "order": 6,
      "isNutrient": true,
      "nutrientName": "ккал"
    }
  ]
}