{
  "name": "Вода детская Агуша 330мл",
  "unitsOfMeasurement": "шт",
  "step": "1.0",
  "priceRegular": "34.99",
  "priceWithCard": "31.84",
  "discountPercent": null,
  "discountedPrice": null,
  "discountIsActive": false,
  "discountExpiresAt": null,
  "isNew": false,
  "stockCount": 6,
  "ingredients": "вода питьевая для детского питания высшей категории негазированная",
  "information": [
    {
      "value": "Агуша",
      "name": "Бренд",
      "unitsOfMeasurement": null,
      "order": 1,
      "isNutrient": false,
      "nutrientName": null
    },
    {
      "value": "Россия",
      "name": "Страна производства",
      "unitsOfMeasurement": null,
      "order": 2,
      "isNutrient": false,
      "nutrientName": null
    }
  ]
}