{
  "name": "Пирожное бисквитное Медвежонок Барни вареная сгущенка 150г",
  "unitsOfMeasurement": "шт",
  "step": "1.0",
  "priceRegular": "159.99",
  "priceWithCard": "155.19",
  "discountPercent": 50,
  "discountedPrice": "77.59",
  "discountIsActive": true,
  "discountExpiresAt": null,
  "isNew": false,
  "stockCount": 35,
  "ingredients": "Мука пшеничная, сироп глюкозно-фруктозный, сахар, яичный продукт, масло растительное (рапсовое), вода, агент влагоудерживающий (глицерин), молоко сухое цельное, крахмал пшеничный, декстроза, молоко сухое обезжиренное, регуляторы кислотности (гидрокарбонат калия, лимонная кислота), разрыхлитель (дигидропирофосфат натрия), соль, эмульгаторы (эфиры глицерина и молочной и жирных кислот, эфиры полиглицерина и жирных кислот, лецитин соевый), карбонат кальция, сироп карамельный, какао-порошок, ароматизаторы натуральные, загуститель (гуаровая камедь).",
  "information": [
    {
      "value": "Медвежонок Барни",
      "name": "Бренд",
      "unitsOfMeasurement": null,
      "order": 1,
      "isNutrient": false,
      "nutrientName": null
    },
    {
      "value": "Россия",
      "name": "Страна производства",
      "unitsOfMeasurement": null,
      "order": 2,
      "isNutrient": false,
      "nutrientName": null
    },
    {
      "value": "5.7",
      "name": "Белки",
      "unitsOfMeasurement": "г",
      "order": 3,
      "isNutrient": true,
      "nutrientName": "белки"
    },
    {
      "value": "16",
      "name": "Жиры",
      "unitsOfMeasurement": "г",
      "order": 4,
      "isNutrient": true,
      "nutrientName": "жиры"
    },
    {
      "value": "52.5",
      "name": "Углеводы",
      "unitsOfMeasurement": "г",
      "order": 5,
      "isNutrient": true,
      "nutrientName": "углеводы"
    },
    {
      "value": "370",
      "name": "Энергетическая ценность",
      "unitsOfMeasurement": "ккал",
      "order": 6,
      "isNutrient": true,
      "nutrientName": "ккал"
    }
  ]
}