{
  "name": "Завтрак готовый Kellogg’s Unicorn Радужные колечки с фруктовым вкусом 195г",
  "unitsOfMeasurement": "шт",
  "step": "1.0",
  "priceRegular": 219.99,
  "priceWithCard": 215.59,
  "promo": null,
  "isNew": false,
  "stockCount": 7,
  "ingredients": "Зерновые родукты (мука пшеничная, хлопья овсяные, крупа кукурузная), сахар,глюкоза, концентраты: редиса, яблока, черной смородины, моркови; краситель:каратины, соль, ароматизатор натуральный тропические фрукты.",
  "information": [
    {
      "value": "Kellogg's",
      "name": "Бренд",
      "unitsOfMeasurement": null,
      "order": 1,
      "isNutrient": false,
      "nutrientName": null
    },
    {
      "value": "Россия",
      "name": "Страна производства",
      "unitsOfMeasurement": null,
      "order": 2,
      "isNutrient": false,
      "nutrientName": null
    },
    {
      "value": "9",
      "name": "Белки",
      "unitsOfMeasurement": "г",
      "order": 3,
      "isNutrient": true,
      "nutrientName": "белки"
    },
    {
      "value": "1.5",
      "name": "Жиры",
      "unitsOfMeasurement": "г",
      "order": 4,
      "isNutrient": true,
      "nutrientName": "жиры"
    },
    {
      "value": "83",
      "name": "Углеводы",
      "unitsOfMeasurement": "г",
      "order": 5,
      "isNutrient": true,
      "nutrientName": "углеводы"
    },
    {
      "value": "380",
      "name": "Энергетическая ценность",
      "unitsOfMeasurement": "ккал",
      "order": 6,
      "isNutrient": true,
      "nutrientName": "ккал"
    }
  ]
}