{
  "name": "Сухари Каскад с изюмом, 300г",
  "unitsOfMeasurement": "шт",
  "step": "1.0",
  "priceRegular": "74.19",
  "priceWithCard": "71.22",
  "discountPercent": null,
  "discountedPrice": null,
  "discountIsActive": false,
  "discountExpiresAt": null,
  "isNew": false,
  "stockCount": 28,
  "ingredients": "Мука пшеничная хлебопекарная (первый сорт, высший сорт), вода питьевая, сахар, виноград сушёный, жир кондитерский (растительные масла, антиокислитель Е306), дрожжи хлебопекарные, соль.",
  "information": [
    {
      "value": "Каскад",
      "name": "Бренд",
      "unitsOfMeasurement": null,
      "order": 1,
      "isNutrient": false,
      "nutrientName": null
    },
    {
      "value": "Россия",
      "name": "Страна производства",
      "unitsOfMeasurement": null,
      "order": 2,
      "isNutrient": false,
      "nutrientName": null
    },
    {
      "value": "8.5",
      "name": "Белки",
      "unitsOfMeasurement": "г",
      "order": 3,
      "isNutrient": true,
      "nutrientName": "белки"
    },
    {
      "value": "9.5",
      "name": "Жиры",
      "unitsOfMeasurement": "г",
      "order": 4,
      "isNutrient": true,
      "nutrientName": "жиры"
    },
    {
      "value": "75",
      "name": "Углеводы",
      "unitsOfMeasurement": "г",
      "order": 5,
      "isNutrient": true,
      "nutrientName": "углеводы"
    },
    {
      "value": "413",
      "name": "Энергетическая ценность",
      "unitsOfMeasurement": "ккал",
      "order": 6,
      "isNutrient": true,
      "nutrientName": "ккал"
    }
  ]
}