{
  "name": "Подгузники Nishoomi 4L 9-14 кг 38шт.",
  "unitsOfMeasurement": "шт",
  "step": "1.0",
  "priceRegular": "1149.00",
  "priceWithCard": "1103.04",
  "discountPercent": 21,
  "discountedPrice": "871.40",
  "discountIsActive": true,
  "discountExpiresAt": null,
  "isNew": true,
  "stockCount": 2,
  "ingredients": "нетканый материал, бамбуковое волокно, суперабсорбент, пленка полиэтиленовая, спандекс, клей",
  "information": [
    {
      "value": "Nishoomi",
      "name": "Бренд",
      "unitsOfMeasurement": null,
      "order": 1,
      "isNutrient": false,
      "nutrientName": null
    },
    {
      "value": "Китай",
      "name": "Страна производства",
      "unitsOfMeasurement": null,
      "order": 2,
      "isNutrient": false,
      "nutrientName": null
    }
  ]
}