{
  "name": "Варенье Варенька абрикосовое 380 г",
  "unitsOfMeasurement": "шт",
  "step": "1.0",
  "priceRegular": 169.99,
  "priceWithCard": 159.79,
  "promo": {
    "discountedPriceRegular": 130.89,
    "discountedPriceWithCard": 123.04,
    "discountPercent": 23,
    "isActive": true
  },
  "isNew": false,
  "stockCount": 13,
  "ingredients": "сахар, абрикос",
  "information": [
    {
      "value": "Варенька",
      "name": "Бренд",
      "unitsOfMeasurement": null,
      "order": 1,
      "isNutrient": false,
      "nutrientName": null
    },
    {
      "value": "Россия",
      "name": "Страна производства",
      "unitsOfMeasurement": null,
      "order": 2,
      "isNutrient": false,
      "nutrientName": null
    },
    {
      "value": "63",
      "name": "Углеводы",
      "unitsOfMeasurement": "г",
      "order": 3,
      "isNutrient": true,
      "nutrientName": "углеводы"
    },
    {
      "value": "252",
      "name": "Энергетическая ценность",
      "unitsOfMeasurement": "ккал",
      "order": 4,
      "isNutrient": true,
      "nutrientName": "ккал"
    }
  ]
}