{
  "name": "Вермишель Домшим фунчоза 200г",
  "unitsOfMeasurement": "шт",
  "step": "1.0",
  "priceRegular": 137.99,
  "priceWithCard": 129.71,
  "promo": null,
  "isNew": false,
  "stockCount": 15,
  "ingredients": null,
  "information": [
    {
      "value": "Домшим",
      "name": "Бренд",
      "unitsOfMeasurement": null,
      "order": 1,
      "isNutrient": false,
      "nutrientName": null
    },
    {
      "value": "Китай",
      "name": "Страна производства",
      "unitsOfMeasurement": null,
      "order": 2,
      "isNutrient": false,
      "nutrientName": null
    }
  ]
}