{
  "name": "Открытка код Ф",
  "unitsOfMeasurement": "шт",
  "step": "1.0",
  "priceRegular": "79.99",
  "priceWithCard": "74.39",
  "discountPercent": null,
  "discountedPrice": null,
  "discountIsActive": false,
  "discountExpiresAt": null,
  "isNew": false,
  "stockCount": 143,
  "ingredients": null,
  "information": [
    {
      "value": "Арт Дизайн",
      "name": "Бренд",
      "unitsOfMeasurement": null,
      "order": 1,
      "isNutrient": false,
      "nutrientName": null
    }
  ]
}