{
  "name": "Напиток Ильинские лимонады Дюшес газированный 1.42л",
  "unitsOfMeasurement": "шт",
  "step": "1.0",
  "priceRegular": 64.99,
  "priceWithCard": 62.39,
  "promo": {
    "discountedPriceRegular": "38.99",
    "discountedPriceWithCard": "37.43",
    "discountPercent": "40",
    "isActive": true
  },
  "isNew": false,
  "stockCount": 6,
  "ingredients": "подготовленная вода, сахар, регуляторы кислотности кислота лимонная и цитрат натрия, концентрированный яблочный сок, ароматизатор, красители сахарный колер 4, подсластители аспартам и ацесульфам калия, консервант бензоат натрия",
  "information": [
    {
      "value": "Ильинские лимонады",
      "name": "Бренд",
      "unitsOfMeasurement": null,
      "order": 1,
      "isNutrient": false,
      "nutrientName": null
    },
    {
      "value": "Россия",
      "name": "Страна производства",
      "unitsOfMeasurement": null,
      "order": 2,
      "isNutrient": false,
      "nutrientName": null
    },
    {
      "value": "5",
      "name": "Углеводы",
      "unitsOfMeasurement": "г",
      "order": 3,
      "isNutrient": true,
      "nutrientName": "углеводы"
    },
    {
      "value": "20",
      "name": "Энергетическая ценность",
      "unitsOfMeasurement": "ккал",
      "order": 4,
      "isNutrient": true,
      "nutrientName": "ккал"
    }
  ]
}