{
  "name": "Картофельное пюре Бизнес Меню с куриным филе и овощими110 г",
  "unitsOfMeasurement": "шт",
  "step": "1.0",
  "priceRegular": "104.99",
  "priceWithCard": "100.79",
  "discountPercent": 28,
  "discountedPrice": "72.57",
  "discountIsActive": true,
  "discountExpiresAt": null,
  "isNew": false,
  "stockCount": 31,
  "ingredients": "хлопья картофельные, заменитель сухого молочного продукта 30% (патока крахмальная, масло пальмовое, казеинат натрия), соль поваренная пищевая, сахар-песок, морковь, лук зеленый, лук репчатый, зелень укропа и петрушки, перец черный, усилитель вкуса – глютамат натрия; филе куриное с приправами: филе куриное, вода, соль поваренная пищевая, лук репчатый, чеснок, морковь, масло растительное, перец черный, перец сладкий, хмели-сунели, куркума",
  "information": [
    {
      "value": "Бизнес Меню",
      "name": "Бренд",
      "unitsOfMeasurement": null,
      "order": 1,
      "isNutrient": false,
      "nutrientName": null
    },
    {
      "value": "Россия",
      "name": "Страна производства",
      "unitsOfMeasurement": null,
      "order": 2,
      "isNutrient": false,
      "nutrientName": null
    },
    {
      "value": "10",
      "name": "Белки",
      "unitsOfMeasurement": "г",
      "order": 3,
      "isNutrient": true,
      "nutrientName": "белки"
    },
    {
      "value": "13.5",
      "name": "Жиры",
      "unitsOfMeasurement": "г",
      "order": 4,
      "isNutrient": true,
      "nutrientName": "жиры"
    },
    {
      "value": "52",
      "name": "Углеводы",
      "unitsOfMeasurement": "г",
      "order": 5,
      "isNutrient": true,
      "nutrientName": "углеводы"
    },
    {
      "value": "370",
      "name": "Энергетическая ценность",
      "unitsOfMeasurement": "ккал",
      "order": 6,
      "isNutrient": true,
      "nutrientName": "ккал"
    }
  ]
}