{
  "name": "Чай Richard Эрл Грей черный с бергамотом в пакетиках 100х2г",
  "unitsOfMeasurement": "шт",
  "step": "1.0",
  "priceRegular": 429.99,
  "priceWithCard": 395.59,
  "promo": {
    "discountedPriceRegular": 262.29,
    "discountedPriceWithCard": 241.31,
    "discountPercent": 39,
    "isActive": true
  },
  "isNew": false,
  "stockCount": 10,
  "ingredients": "цейлонский черный байховый чай, ароматизатор бергамот",
  "information": [
    {
      "value": "Richard",
      "name": "Бренд",
      "unitsOfMeasurement": null,
      "order": 1,
      "isNutrient": false,
      "nutrientName": null
    },
    {
      "value": "Россия",
      "name": "Страна производства",
      "unitsOfMeasurement": null,
      "order": 2,
      "isNutrient": false,
      "nutrientName": null
    }
  ]
}