{
  "name": "Чай Майский Отборный черный цейлонский в пакетиках 100х2г",
  "unitsOfMeasurement": "шт",
  "step": "1.0",
  "priceRegular": "279.99",
  "priceWithCard": "274.39",
  "discountPercent": 32,
  "discountedPrice": "186.59",
  "discountIsActive": true,
  "discountExpiresAt": null,
  "isNew": false,
  "stockCount": 4,
  "ingredients": "цейлонский мелколистовой черный чай",
  "information": [
    {
      "value": "Майский",
      "name": "Бренд",
      "unitsOfMeasurement": null,
      "order": 1,
      "isNutrient": false,
      "nutrientName": null
    },
    {
      "value": "Россия",
      "name": "Страна производства",
      "unitsOfMeasurement": null,
      "order": 2,
      "isNutrient": false,
      "nutrientName": null
    }
  ]
}