{
  "name": "Чай Curtis Sunny Lemon черный в пакетиках 20х1.47г",
  "unitsOfMeasurement": "шт",
  "step": "1.0",
  "priceRegular": "139.99",
  "priceWithCard": "130.19",
  "discountPercent": 39,
  "discountedPrice": "79.42",
  "discountIsActive": true,
  "discountExpiresAt": null,
  "isNew": false,
  "stockCount": 13,
  "ingredients": "Листовой черный чай, ароматизатор лимон, цедра цитрусовых, лепестки подсолнечника.",
  "information": [
    {
      "value": "Curtis",
      "name": "Бренд",
      "unitsOfMeasurement": null,
      "order": 1,
      "isNutrient": false,
      "nutrientName": null
    },
    {
      "value": "Россия",
      "name": "Страна производства",
      "unitsOfMeasurement": null,
      "order": 2,
      "isNutrient": false,
      "nutrientName": null
    }
  ]
}