{
  "name": "Кофе Московская кофейня на паяхъ Суаре растворимый сублимированный 95г",
  "unitsOfMeasurement": "шт",
  "step": "1.0",
  "priceRegular": 359.99,
  "priceWithCard": 345.59,
  "promo": {
    "discountedPriceRegular": "251.99",
    "discountedPriceWithCard": "241.91",
    "discountPercent": "30",
    "isActive": true
  },
  "isNew": false,
  "stockCount": 10,
  "ingredients": "Кофе натуральный растворимый сублимированный.",
  "information": [
    {
      "value": "Суаре",
      "name": "Бренд",
      "unitsOfMeasurement": null,
      "order": 1,
      "isNutrient": false,
      "nutrientName": null
    },
    {
      "value": "Россия",
      "name": "Страна производства",
      "unitsOfMeasurement": null,
      "order": 2,
      "isNutrient": false,
      "nutrientName": null
    }
  ]
}