{
  "name": "Бальзам после бритья Nivea Men успокаивающий 100мл",
  "unitsOfMeasurement": "шт",
  "step": "1.0",
  "priceRegular": 569.99,
  "priceWithCard": 535.79,
  "promo": null,
  "isNew": false,
  "stockCount": 11,
  "ingredients": "Aqua, Glycerin, Isopropyl Palmitate, Chamomilla Recutita Flower Extract, Tocopheryl Acetate, Hamamelis Virginiana Bark/Leaf Extract, Maltodextrin, Tapioca Starch, Triceteareth-4 Phosphate, Sodium Carbomer, Caprylic/Capric Triglyceride, Phenoxyethanol, Piroctone Olamine, Parfum.",
  "information": [
    {
      "value": "Nivea",
      "name": "Бренд",
      "unitsOfMeasurement": null,
      "order": 1,
      "isNutrient": false,
      "nutrientName": null
    },
    {
      "value": "Германия",
      "name": "Страна производства",
      "unitsOfMeasurement": null,
      "order": 2,
      "isNutrient": false,
      "nutrientName": null
    }
  ]
}