{
  "name": "Пластырь Econta медицинский 20шт",
  "unitsOfMeasurement": "шт",
  "step": "1.0",
  "priceRegular": 69.99,
  "priceWithCard": 68.59,
  "promo": null,
  "isNew": true,
  "stockCount": 6,
  "ingredients": "Основа: полимерная пленка с перфорацией. Адгезивный слой: гипоаллергенный полиакрилатный клей",
  "information": [
    {
      "value": "Econta",
      "name": "Бренд",
      "unitsOfMeasurement": null,
      "order": 1,
      "isNutrient": false,
      "nutrientName": null
    },
    {
      "value": "Великобритания",
      "name": "Страна производства",
      "unitsOfMeasurement": null,
      "order": 2,
      "isNutrient": false,
      "nutrientName": null
    }
  ]
}